exts/__init__.py
exts/smtp.py
exts/sqlalchemy.py
exts/uploads.py
libs/__init__.py
libs/decorators.py
libs/encoder.py
libs/formatters.py
libs/helpers.py
libs/util.py
malwarescan/__init__.py
malwarescan/app.py
malwarescan/celery.py
malwarescan/cli.py
malwarescan/config.py
malwarescan/wsclient.py
malwarescan/wsgi.py
malwarescan/static/favicon.ico
malwarescan/static/admin/css/bootstrap3/admin.css
malwarescan/static/admin/css/bootstrap3/bootstrap-theme.css
malwarescan/static/admin/css/bootstrap3/bootstrap.css
malwarescan/static/admin/css/bootstrap3/rediscli.css
malwarescan/static/admin/css/bootstrap3/submenu.css
malwarescan/static/admin/js/actions.js
malwarescan/static/admin/js/bs2_modal.js
malwarescan/static/admin/js/bs3_modal.js
malwarescan/static/admin/js/details_filter.js
malwarescan/static/admin/js/filters.js
malwarescan/static/admin/js/form.js
malwarescan/static/admin/js/rediscli.js
malwarescan/static/admin/js/bootstrap3/bootstrap.js
malwarescan/static/admin/js/bootstrap3/bootstrap.min.js
malwarescan/static/admin/vendor/jquery.min.js
malwarescan/static/admin/vendor/moment.min.js
malwarescan/static/admin/vendor/bootstrap-daterangepicker/README.md
malwarescan/static/admin/vendor/bootstrap-daterangepicker/daterangepicker-bs2.css
malwarescan/static/admin/vendor/bootstrap-daterangepicker/daterangepicker-bs3.css
malwarescan/static/admin/vendor/bootstrap-daterangepicker/daterangepicker.js
malwarescan/static/admin/vendor/leaflet/leaflet.css
malwarescan/static/admin/vendor/leaflet/leaflet.draw.css
malwarescan/static/admin/vendor/leaflet/leaflet.draw.js
malwarescan/static/admin/vendor/leaflet/leaflet.js
malwarescan/static/admin/vendor/leaflet/images/layers-2x.png
malwarescan/static/admin/vendor/leaflet/images/layers.png
malwarescan/static/admin/vendor/leaflet/images/marker-icon-2x.png
malwarescan/static/admin/vendor/leaflet/images/marker-icon.png
malwarescan/static/admin/vendor/leaflet/images/marker-shadow.png
malwarescan-0.0.1.dist-info/LICENSE
malwarescan-0.0.1.dist-info/METADATA
malwarescan-0.0.1.dist-info/WHEEL
malwarescan-0.0.1.dist-info/entry_points.txt
malwarescan-0.0.1.dist-info/top_level.txt
malwarescan-0.0.1.dist-info/RECORD
