Metadata-Version: 2.1
Name: malwarescan
Version: 0.0.1
Summary: MalwareScan Framework - Unified API frontend to various malware     analysis and sandboxing backends.
Home-page: https://github.com/lbahtarliev/malwarescan
Author: Lyuben Bahtarliev
Author-email: lyuben.bahtarliev@akat-t.com
License: The Unlicense - http://unlicense.org/
Keywords: Swagger,MalwareScan,Malware,Content Analysis,Sandbox
Platform: UNKNOWN
Requires-Dist: celery
Requires-Dist: connexion
Requires-Dist: cryptography
Requires-Dist: Flask
Requires-Dist: Flask-Admin
Requires-Dist: Flask-AppFactory
Requires-Dist: Flask-CeleryExt
Requires-Dist: Flask-Mail
Requires-Dist: Flask-SQLAlchemy
Requires-Dist: Flask-Uploads
Requires-Dist: psycopg2-binary
Requires-Dist: websocket-client
